Workbook

Sheet Start Here
A1: Burton Inn: permitting and licensing workbook
A2: 24007 Vashon Hwy SW, Vashon, WA 98070 (unincorporated King County). Built Oct 13, 2026 from the research task.
A4: Key numbers
B5: Low | C5: High
A6: Rooms only: weeks until first guest can book | B6: ='Rooms Only'!I18 -> 3 | C6: ='Rooms Only'!J18 -> 8 | D6: From the Rooms Only tab. Set its scenario switch to include the occupancy-review add-on.
A7: Rooms only: one-time cost, known items ($) | B7: =Costs!D22 -> 150 | C7: =Costs!E22 -> 650 | D7: Excludes items with no number yet; see Costs.
A8: Kitchen and liquor: weeks to open | B8: 24 | C8: 32 | D8: From the Critical Path tab; assumes the septic does not need a major redesign.
A9: Kitchen and liquor: one-time cost ($) | B9: =Costs!D23 -> 28364 | C9: =Costs!E23 -> 308200 | D9: Septic upgrade is the wild card (zero to $150,000).
A11: Permit tracker (from Master List)
A12: Open | B12: =COUNTIF('Master List'!J6:J25,A12) -> 20
A13: In progress | B13: =COUNTIF('Master List'!J6:J25,A13) -> 0
A14: Done | B14: =COUNTIF('Master List'!J6:J25,A14) -> 0
A15: N/A | B15: =COUNTIF('Master List'!J6:J25,A15) -> 0
A17: What to know first
A18: The kitchen, not the liquor license, is the critical path. It has been closed more than 365 days, so Public Health requires a full plan review.
A19: Burton is almost certainly on septic. Grease handling and septic capacity are the likeliest deal-breakers for the restaurant.
A20: The roofless Type I hood needs King County mechanical and fire suppression permits before Public Health will do its preoperational inspection.
A21: The liquor license takes 60 to 90 days and runs in parallel. File about 90 days before the target open date.
A22: The rooms do not depend on any of that. Their gate is the zoning letter and the lease check.
A23: No true stopgap liquor license exists for a for-profit business. Special Occasion licenses are for nonprofits only.
A25: Caveats
A26: Zoning, septic status, water provider and landmark status come from secondary sources and are not confirmed against official King County records. Treat them as leads.
A27: Cost ranges marked estimate are planning figures, not quotes. Fees marked 'per 2026 schedule' were not retrieved.
A28: The 2024 building codes take effect May 3, 2027. Rules after that date may differ.
A29: This is not legal advice. Confirm with LCB, King County DLS and Public Health.
A31: Legend
A32: Blue text on yellow | B32: Cells you edit: status, start weeks, include switches, assumptions.
A33: Green text | B33: Pulled from another tab.
A34: Black text | B34: Formulas and research findings. Leave alone.
A36: Tabs
A37: Rooms Only | B37: Fastest path: just the 4 upstairs rooms
A38: Master List | B38: All 20 permits and licenses with status
A39: Alcohol Paths | B39: License types compared, partner's mobile bar, structure options
A40: Lodging | B40: R-1 vs R-3 vs B&B vs 30+ day
A41: Kitchen | B41: Reactivation checklist
A42: Critical Path | B42: Week-by-week chart for kitchen and liquor
A43: Costs | B43: Low and high estimates with totals
A44: Open Questions | B44: Records to request and decisions to make
A45: Sources | B45: Every link with a reliability flag

Sheet Rooms Only
A1: Rooms only: opening the 4 upstairs rooms as short-term rentals
A2: No kitchen, septic or liquor license needed for this path. Weeks are counted from today. Blue on yellow cells are yours to edit.
A4: # | B4: Task | C4: Who | D4: Depends on | E4: Start low (wk) | F4: Start high (wk) | G4: Duration low (wk) | H4: Duration high (wk) | I4: End low (wk) | J4: End high (wk) | K4: Fee | L4: Status | M4: Notes
A5: 1 | B5: Request permit history and Certificate of Occupancy (1993 permit, occupancy class, expired permits, code enforcement) | C5: Owner | D5: None | E5: 0 | F5: 0 | G5: 2 | H5: 6 | I5: =E5+G5 -> 2 | J5: =F5+H5 -> 6 | K5: Copy fees only | L5: Open | M5: King County Permitting Records Center. Informs the occupancy risk row below. Not a hard gate for go-live.
A6: 2 | B6: Zoning and Historical Certification Letter; confirm lodging use is allowed and read the P-suffix text | C6: Owner / architect | D6: None | E6: 0 | F6: 0 | G6: 2 | H6: 6 | I6: =E6+G6 -> 2 | J6: =F6+H6 -> 6 | K6: Per KC 2026 fee schedule | L6: Open | M6: THE gate. Zoning is probably NB-P but unconfirmed. If a B&B guesthouse needs a resident operator, the plan changes.
A7: 3 | B7: Confirm the lease allows nightly lodging; get landlord consent in writing | C7: Owner | D7: None | E7: 0 | F7: 0 | G7: 1 | H7: 2 | I7: =E7+G7 -> 1 | J7: =F7+H7 -> 2 | K7: None | L7: Open | M7: Do this before spending money on anything else.
A8: 4 | B8: WA business license for Burton Inn LLC; register for lodging and sales tax | C8: Owner | D8: None | E8: 0 | F8: 0 | G8: 1 | H8: 3 | I8: =E8+G8 -> 1 | J8: =F8+H8 -> 3 | K8: $50 application fee | L8: Open | M8: DOR Business Licensing Service. Airbnb collects most lodging taxes but you still file returns.
A9: 5 | B9: Liability insurance ($1M or equivalent platform coverage) and RCW 64.37 postings (safety and contact info) | C9: Owner | D9: None | E9: 0 | F9: 0 | G9: 1 | H9: 2 | I9: =E9+G9 -> 1 | J9: =F9+H9 -> 2 | K9: Premium: get a quote | L9: Open | M9: State short-term rental law. Check that the policy covers nightly rentals of a commercial building.
A10: 6 | B10: Smoke and CO alarm check in every room and the egress path; set guest cap (10 vs 16) | C10: Owner / contractor | D10: Task 3 | E10: =I7 -> 1 | F10: =J7 -> 2 | G10: 1 | H10: 2 | I10: =E10+G10 -> 2 | J10: =F10+H10 -> 4 | K10: Alarms: see Costs | L10: Open | M10: Cap of 10 guests total likely keeps the rooms in the cheaper R-3 category. 16 means R-1.
A11: 7 | B11: Listing setup: photos, house rules, tax collection settings | C11: Owner | D11: Task 2 | E11: =I6 -> 2 | F11: =J6 -> 6 | G11: 1 | H11: 2 | I11: =E11+G11 -> 3 | J11: =F11+H11 -> 8 | K11: None | L11: Open | M11: Do not publish before the zoning answer is in hand.
A12: 8 | B12: GO LIVE: all of the above complete | D12: Tasks 2 to 7 | E12: =MAX(I6,I8,I9,I10,I11) -> 3 | F12: =MAX(J6,J8,J9,J10,J11) -> 8 | G12: 0 | H12: 0 | I12: =E12+G12 -> 3 | J12: =F12+H12 -> 8 | L12: Open | M12: Earliest and latest week the first guest can book, if no occupancy surprise turns up.
B14: Scenarios | I14: Low (wk) | J14: High (wk)
B15: Base case: first guest can book | I15: =I12 -> 3 | J15: =J12 -> 8
B16: Add-on if records show no lodging occupancy history, so a change of occupancy review is needed (my estimate, weeks) | I16: 8 | J16: 24
B17: Include the add-on? 1 = yes, 0 = no | I17: 0
B18: Go-live with the selected scenario | I18: =I15+I17*I16 -> 3 | J18: =J15+I17*J16 -> 8
B20: Decisions only you can make
B21: Guest cap: 10 total (likely R-3, cheaper) or up to 16 (R-1, more revenue, more fire and egress scrutiny).
B22: Whether you or an on-site manager will live in the building. A bed and breakfast guesthouse classification may require a resident operator (secondary source, verify).
B23: Accessibility: rooms are upstairs only. Repairs alone do not trigger upgrades, but document a feasibility note in case the county asks.

Sheet Master List
A1: Master permit and license list
A2: 20 items from the research. Fees and times marked (est.) are planning estimates. Status is yours to edit.
A5: # | B5: Item | C5: Applies to | D5: Needed for rooms only? | E5: Agency / portal | F5: Fee (source) | G5: Typical time | H5: Prerequisites | I5: Who | J5: Status | K5: Notes
A6: 1 | B6: Records requests: permits, CO, code enforcement, OSS as-built, PH inspections, LCB history | C6: Both | D6: Yes | E6: KC Permitting Records Center; PHSKC; LCB Public Records | F6: Copy fees only (est.) | G6: 2 to 6 wks | H6: None | I6: Owner | J6: Open
A7: 2 | B7: Zoning and Historical Certification Letter / pre-application meeting | C7: Both | D7: Yes | E7: KC DLS via MyBuildingPermit.com | F7: Per 2026 KC fee schedule (2025 fees rose 49%) | G7: 2 to 6 wks (est.) | H7: Parcel number | I7: Owner / architect | J7: Open | K7: Confirms NB-P zoning, P-suffix text, and whether lodging and restaurant uses are allowed.
A8: 3 | B8: WA business license, UBI, trade name | C8: Both | D8: Yes | E8: DOR Business Licensing Service | F8: $50 application handling fee (WAC 458-02-200) | G8: 1 to 3 wks | H8: LLC formed | I8: Owner | J8: Open
A9: 4 | B9: Septic evaluation by certified On-site System Maintainer | C9: Kitchen | D9: No | E9: Private OSM; report to PHSKC | F9: $500 to $1,500 (est.) | G9: 1 to 3 wks | H9: OSS as-built | I9: Owner | J9: Open | K9: Burton is almost certainly on septic, not the Vashon Sewer District.
A10: 5 | B10: OSS design or modification, grease interceptor | C10: Kitchen | D10: No | E10: PHSKC OSS program plus licensed designer | F10: Fee schedule BOH 2.18; design $3k to $10k (est.) | G10: 6 to 16 wks (est.) | H10: Septic evaluation | I10: Designer / installer | J10: Open | K10: Biggest swing factor in cost and time.
A11: 6 | B11: Water service and backflow confirmation | C11: Kitchen | D11: No | E11: Burton Water Co-op (verify) | F11: Unknown | G11: 1 to 4 wks | H11: None | I11: Owner / plumber | J11: Open
A12: 7 | B12: Food plan review (full, because closed more than 365 days) | C12: Kitchen | D12: No | E12: PHSKC Permit Center | F12: $1,008 base + $252 per extra hour (PHSKC 2026) | G12: About 2 to 8 wks | H12: Menu, equipment plan, septic direction | I12: Owner / designer | J12: Open
A13: 8 | B13: Mechanical permit: Type I hood, roof fan, makeup air | C13: Kitchen | D13: No | E13: KC DLS | F13: Per 2026 fee schedule | G13: 3 to 10 wks (est.) | H13: Hood engineering | I13: Mechanical contractor | J13: Open | K13: Roof fan was removed. With no documents, assume listing, duct and suppression need recertifying.
A14: 9 | B14: Fire suppression (UL 300) permit and test | C14: Kitchen | D14: No | E14: KC Fire Marshal | F14: Per 2026 fee schedule | G14: 2 to 6 wks (est.) | H14: Hood design | I14: Fire contractor | J14: Open
A15: 10 | B15: Electrical permit | C15: Kitchen | D15: No | E15: WA L&I (inferred) | F15: Per L&I schedule | G15: Days to 2 wks | H15: None | I15: Electrician | J15: Open
A16: 11 | B16: Plumbing permit: sinks, interceptor | C16: Kitchen | D16: No | E16: PHSKC plumbing (inferred) | F16: Per PHSKC schedule | G16: 1 to 3 wks | H16: Food plan review | I16: Plumber | J16: Open
A17: 12 | B17: Building permit, only if any alteration goes beyond repair | C17: Both | D17: If needed | E17: KC DLS | F17: Per 2026 fee schedule | G17: 4 to 16 wks (est.) | H17: Zoning letter, mechanical | I17: Architect | J17: Open | K17: Conditional.
A18: 13 | B18: Final inspections and CO confirmation | C18: Both | D18: If needed | E18: KC DLS; Fire Marshal | F18: Included | G18: 1 to 3 wks | H18: Trade permits closed | I18: Contractor | J18: Open
A19: 14 | B19: PH preoperational inspection and annual operating permit | C19: Kitchen | D19: No | E19: PHSKC | F19: $756 (Risk 2) or $1,008 (Risk 3), 13 to 50 seats | G19: 1 to 2 wks after finals | H19: Plan review, finals | I19: Owner | J19: Open | K19: Risk level depends on the menu.
A20: 15 | B20: LCB liquor license | C20: Alcohol | D20: No | E20: LCB via DOR Business Licensing Service | F20: $600 (beer/wine) or $2,200 to $2,700 (spirits, beer and wine) a year | G20: 60 to 90 days | H20: Business license, lease, floor plan | I20: Owner | J20: Open | K20: File about 90 days before the target open date.
A21: 16 | B21: MAST permits (Class 12 or 13) for every server | C21: Alcohol | D21: No | E21: LCB-certified trainers | F21: Trainer fee (verify) | G21: 1 day | H21: Hire | I21: Staff | J21: Open
A22: 17 | B22: Food worker cards; Certified Food Protection Manager | C22: Kitchen | D22: No | E22: WA DOH online; ANSI exam | F22: Card fee (verify) | G22: 1 day | H22: None | I22: Staff | J22: Open | K22: CFPM expectation not verified.
A23: 18 | B23: Short-term rental compliance: RCW 64.37 insurance and postings | C23: Rooms | D23: Yes | E23: Self / insurer | F23: Premium | G23: 1 to 2 wks | H23: Zoning letter | I23: Owner | J23: Open
A24: 19 | B24: Fire operational permits and annual inspection | C24: Kitchen | D24: No | E24: KC Fire Marshal | F24: Not published by VIFR; KC schedule | G24: Annual | H24: Finals | I24: Owner | J24: Open | K24: Unincorporated Vashon falls under the King County Fire Marshal.
A25: 20 | B25: Sign permit | C25: Both | D25: No | E25: KC DLS (KCC 21A.20.095) | F25: Per 2026 schedule | G25: 2 to 6 wks | H25: Zoning letter | I25: Sign company | J25: Open | K25: Optional.

Sheet Alcohol Paths
A1: Alcohol license paths (on-premise only)
A2: Fees are LCB 2026 annual figures from the research. Fit column is my read, not LCB's.
A4: Path | B4: Eligibility and food rules | C4: Privileges | D4: Limits | E4: Annual fee | F4: Fit for Burton Inn
A5: 1. Spirits, Beer and Wine Restaurant | B5: Bona fide restaurant: 4 complete meals cooked on site, cook on duty, menu, kitchen equipment (WAC 314-02-035). Under 100% dining: complete meals at least 5 hrs a day, 3 days a week, between 8 a.m. and 11 p.m. | C5: Full bar; catering endorsement ($525); premixed cocktails to go with a meal; off-premises wine ($180) | D5: Hood and full kitchen must be live; meal records required | E5: $2,200 (50%+ dining), $2,700 (under 50%), $1,400 (service bar) | F5: Best if a real menu is planned
A6: 2. Beer and/or Wine Restaurant | B6: Minimum food service (sandwiches, soup, pizza, etc.) | C6: Beer and wine on tap or opened; catering, off-premises and wine-to-go endorsements | D6: No spirits | E6: $300 beer, $300 wine, $600 both | F6: Lowest-risk start; can upgrade later
A7: 3. Beer and/or Wine Tavern | B7: No food requirement listed | C7: Beer and wine on premises; catering endorsement | D7: No one under 21 on premises at any time | E7: $300 / $300 / $600 | F7: Poor fit for an inn and family dining
A8: 4. Snack Bar | B8: Snack food; designated seating | C8: Beer by opened bottle or can, wine by the glass | D8: No taps; beer cannot be the principal business | E8: $187.50 | F8: Possible if the kitchen is delayed
A9: 5. Catering endorsement | B9: Needs an underlying restaurant or tavern license | C9: Serve at unlicensed off-site events | D9: Not at other licensed premises | E9: $525 | F9: Lets the Inn do off-site events, separate from the partner
A10: 6. Special Occasion / banquet | B10: Special Occasion: bona fide nonprofits only, 12 single-day events a year. Banquet: invitation only, no charge for liquor | C10: Short events | D10: Retail licensees cannot get banquet permits; no third-party promoter cut on Special Occasion | E10: $90 a day; $25 a day | F10: Only a nonprofit-hosted bridge. No real stopgap for a for-profit.
A11: 7. Hotel / Motel | B11: Hotel requires 20+ rooms. Motel license allows honor bars in up to 50% of rooms | C11: In-room alcohol | D11: 4 rooms fails the hotel test; motel eligibility unverified | E11: $2,500 / $750 | F11: Likely not available
A13: Partner's mobile bar
A14: LCB liquor caterer licenses are prohibited from catering events at liquor-licensed premises. Once the Inn is licensed, the partner's separate business cannot pour at the Inn under its own license. Partner staff can work Inn events as Burton Inn LLC employees with MAST permits, using the Inn's inventory.
A16: Structure options
A17: (a) Burton Inn LLC holds the license and operates | B17: Simplest. The lease must allow it.
A18: (b) Operator (partner's company) subleases the kitchen and bar and holds the license | B18: Operator needs its own lease or sublease, UBI and Public Health permit. Burton Inn LLC cannot share in alcohol revenue without being disclosed.
A19: (c) Management agreement with Burton Inn LLC as licensee | B19: Must be disclosed to and reviewed by LCB.
A21: Alcohol in the guest rooms
A22: A restaurant license covers only the floor-plan premises. Welcome bottles bundled into a paid stay are a likely unlicensed sale. Do not do it without written LCB guidance.
A24: LCB process
A25: Step 1 | B25: File through DOR Business Licensing Service no more than 90 days before opening (needs a business address).
A26: Step 2 | B26: Licensing specialist contacts you within about a week. Phase 1 takes about 10 days.
A27: Step 3 | B27: LCB notifies King County, which has 20 days to respond (60 in an Alcohol Impact Area; Burton is not one, verify).
A28: Step 4 | B28: Public notice posted at the premises for 14 days.
A29: Step 5 | B29: You submit business structure, financing sources, lease and floor plan. Principals are fingerprinted.
A30: Step 6 | B30: On approval, an approval letter acts as a 30-day license until the business license with liquor endorsement arrives. Typical total: 60 to 90 days.

Sheet Lodging
A1: Lodging classification comparison (4 upstairs rooms)
A2: Occupancy classes are inferred from the 2021 IBC; confirm against the 1993 permit and Certificate of Occupancy.
A4: Path | B4: Code occupancy | C4: Zoning use | D4: Guests | E4: Key trade-off
A5: Inn rooms, up to 16 guests | B5: R-1 | C5: Hotel/motel or B&B (verify in NB zone) | D5: 16 | E5: Most revenue; highest fire and egress scrutiny
A6: Transient lodging house, 10 guests or fewer | B6: R-3 (5 or fewer rooms, 10 or fewer occupants) | C6: Same as above | D6: 10 | E6: Cheapest code path
A7: B&B guesthouse | B7: R-3 likely | C7: B&B guesthouse (5 rooms or fewer; residency condition reported by one secondary source) | D7: 10 | E7: Needs a resident operator if that condition is confirmed
A8: 30+ day rentals | B8: R-2 or R-3 | C8: Residential per NB rules | E8: Avoids short-term rental taxes; tenant law applies
A10: Other points
A11: Washington RCW 64.37 defines a short-term rental as lodging that is not a hotel, motel or bed and breakfast, and excludes a duly licensed inn or hotel. Unincorporated King County has no dedicated STR permit program (secondary sources; verify).
A12: Parking (KCC 21A.18): B&B guesthouse needs 1 space per guest room plus 2 per facility (6 total for 4 rooms). Hotel/motel needs 1 per bedroom. The restaurant adds its own requirement.
A13: Downstairs: a 40-seat dining room with an occupant load under 50 is generally Group B. Fifty or more makes it A-2, which raises egress and fire alarm demands.
A14: Accessibility: repairs do not trigger upgrades. Alterations to primary-function areas can, with a 20% disproportionate-cost cap and technical infeasibility exceptions. The federal ADA lodging exemption likely does not apply unless the proprietor lives on site.
A15: Codes: 2021 codes apply now. The 2024 codes take effect May 3, 2027; permits applied for before then should be reviewed under the 2021 codes.

Sheet Kitchen
A1: Kitchen reactivation checklist
A2: Assumes no equipment documents survive. Status is yours to edit.
A4: # | B4: Area | C4: What to do | D4: Who | E4: Status
A5: 1 | B5: Equipment inventory | C5: List every remaining item with make, model and NSF/UL labels. | D5: Owner | E5: Open
A6: 2 | B6: Hood | C6: Get the UL listing and a duct inspection. Replace the roof upblast fan. Install makeup air. Get an NFPA 96 cleaning certificate. | D6: Mechanical contractor | E6: Open
A7: 3 | B7: Suppression | C7: Install a new or recertified UL 300 system with fuel shutoff and a K-class extinguisher. | D7: Fire contractor | E7: Open
A8: 4 | B8: Sinks | C8: Handwashing sinks, 3-compartment sink, prep sink, mop sink. Check water heater capacity. | D8: Plumber | E8: Open
A9: 5 | B9: Grease | C9: Exterior interceptor sized to UPC 2021, with a maintenance schedule filed with the septic design. | D9: Designer / installer | E9: Open
A10: 6 | B10: Septic | C10: OSM inspection and flow and strength review. | D10: Certified OSM | E10: Open
A11: 7 | B11: Refrigeration and finishes | C11: Refrigeration, thermometers, smooth and cleanable finishes. | D11: Contractor | E11: Open
A12: 8 | B12: Plan submittal | C12: Floor plan and menu to Public Health. Set the risk level. | D12: Owner / designer | E12: Open
A13: 9 | B13: People | C13: Food worker cards; Certified Food Protection Manager. | D13: Staff | E13: Open
A14: 10 | B14: Inspection | C14: Preoperational inspection; operating permit posted. | D14: Owner | E14: Open

Sheet Critical Path
A1: Critical path: kitchen and liquor (weeks from today)
A2: Estimates from the research. Change the target open week and the LCB lead time to see the liquor filing window move.
B3: Target open week (assumption, midpoint of 24 to 32) | C3: 28
B4: LCB lead time in weeks (90 days is about 13) | C4: 13
A5: # | B5: Activity | C5: Start wk | D5: End wk | E5: Weeks | F5: 0 | G5: 1 | H5: 2 | I5: 3 | J5: 4 | K5: 5 | L5: 6 | M5: 7 | N5: 8 | O5: 9 | P5: 10 | Q5: 11 | R5: 12 | S5: 13 | T5: 14 | U5: 15 | V5: 16 | W5: 17 | X5: 18 | Y5: 19 | Z5: 20 | AA5: 21 | AB5: 22 | AC5: 23 | AD5: 24 | AE5: 25 | AF5: 26 | AG5: 27 | AH5: 28 | AI5: 29 | AJ5: 30 | AK5: 31 | AL5: 32
A6: 1 | B6: Records requests, zoning letter, septic inspection, equipment inventory, LLC and UBI | C6: 0 | D6: 4 | E6: =D6-C6 -> 4 | F6: =IF(AND(F$5>=$C6,F$5<$D6),1,"") -> 1 | G6: =IF(AND(G$5>=$C6,G$5<$D6),1,"") -> 1 | H6: =IF(AND(H$5>=$C6,H$5<$D6),1,"") -> 1 | I6: =IF(AND(I$5>=$C6,I$5<$D6),1,"") -> 1 | J6: =IF(AND(J$5>=$C6,J$5<$D6),1,"") | K6: =IF(AND(K$5>=$C6,K$5<$D6),1,"") | L6: =IF(AND(L$5>=$C6,L$5<$D6),1,"") | M6: =IF(AND(M$5>=$C6,M$5<$D6),1,"") | ... AL6: =IF(AND(AL$5>=$C6,AL$5<$D6),1,"")
A7: 2 | B7: Hood, fan and makeup air design; septic and grease design; Public Health plan submittal | C7: 4 | D7: 12 | E7: =D7-C7 -> 8 | F7: =IF(AND(F$5>=$C7,F$5<$D7),1,"") | G7: =IF(AND(G$5>=$C7,G$5<$D7),1,"") | H7: =IF(AND(H$5>=$C7,H$5<$D7),1,"") | I7: =IF(AND(I$5>=$C7,I$5<$D7),1,"") | J7: =IF(AND(J$5>=$C7,J$5<$D7),1,"") -> 1 | K7: =IF(AND(K$5>=$C7,K$5<$D7),1,"") -> 1 | L7: =IF(AND(L$5>=$C7,L$5<$D7),1,"") -> 1 | M7: =IF(AND(M$5>=$C7,M$5<$D7),1,"") -> 1 | ... AL7: =IF(AND(AL$5>=$C7,AL$5<$D7),1,"")
A8: 3 | B8: Permits issued: mechanical, fire, plumbing, OSS | C8: 8 | D8: 20 | E8: =D8-C8 -> 12 | F8: =IF(AND(F$5>=$C8,F$5<$D8),1,"") | G8: =IF(AND(G$5>=$C8,G$5<$D8),1,"") | H8: =IF(AND(H$5>=$C8,H$5<$D8),1,"") | I8: =IF(AND(I$5>=$C8,I$5<$D8),1,"") | J8: =IF(AND(J$5>=$C8,J$5<$D8),1,"") | K8: =IF(AND(K$5>=$C8,K$5<$D8),1,"") | L8: =IF(AND(L$5>=$C8,L$5<$D8),1,"") | M8: =IF(AND(M$5>=$C8,M$5<$D8),1,"") | ... AL8: =IF(AND(AL$5>=$C8,AL$5<$D8),1,"")
A9: 4 | B9: Construction | C9: 12 | D9: 28 | E9: =D9-C9 -> 16 | F9: =IF(AND(F$5>=$C9,F$5<$D9),1,"") | G9: =IF(AND(G$5>=$C9,G$5<$D9),1,"") | H9: =IF(AND(H$5>=$C9,H$5<$D9),1,"") | I9: =IF(AND(I$5>=$C9,I$5<$D9),1,"") | J9: =IF(AND(J$5>=$C9,J$5<$D9),1,"") | K9: =IF(AND(K$5>=$C9,K$5<$D9),1,"") | L9: =IF(AND(L$5>=$C9,L$5<$D9),1,"") | M9: =IF(AND(M$5>=$C9,M$5<$D9),1,"") | ... AL9: =IF(AND(AL$5>=$C9,AL$5<$D9),1,"")
A10: 5 | B10: LCB application window (file about 90 days before target open) | C10: =C3-C4 -> 15 | D10: =C3 -> 28 | E10: =D10-C10 -> 13 | F10: =IF(AND(F$5>=$C10,F$5<$D10),1,"") | G10: =IF(AND(G$5>=$C10,G$5<$D10),1,"") | H10: =IF(AND(H$5>=$C10,H$5<$D10),1,"") | I10: =IF(AND(I$5>=$C10,I$5<$D10),1,"") | J10: =IF(AND(J$5>=$C10,J$5<$D10),1,"") | K10: =IF(AND(K$5>=$C10,K$5<$D10),1,"") | L10: =IF(AND(L$5>=$C10,L$5<$D10),1,"") | M10: =IF(AND(M$5>=$C10,M$5<$D10),1,"") | ... AL10: =IF(AND(AL$5>=$C10,AL$5<$D10),1,"")
A11: 6 | B11: Finals, Public Health preoperational inspection, LCB approval, open | C11: 24 | D11: 32 | E11: =D11-C11 -> 8 | F11: =IF(AND(F$5>=$C11,F$5<$D11),1,"") | G11: =IF(AND(G$5>=$C11,G$5<$D11),1,"") | H11: =IF(AND(H$5>=$C11,H$5<$D11),1,"") | I11: =IF(AND(I$5>=$C11,I$5<$D11),1,"") | J11: =IF(AND(J$5>=$C11,J$5<$D11),1,"") | K11: =IF(AND(K$5>=$C11,K$5<$D11),1,"") | L11: =IF(AND(L$5>=$C11,L$5<$D11),1,"") | M11: =IF(AND(M$5>=$C11,M$5<$D11),1,"") | ... AL11: =IF(AND(AL$5>=$C11,AL$5<$D11),1,"")
A12: 7 | B12: Rooms-only go-live window (low to high, from the Rooms Only tab) | C12: ='Rooms Only'!I18 -> 3 | D12: ='Rooms Only'!J18 -> 8 | E12: =D12-C12 -> 5 | F12: =IF(AND(F$5>=$C12,F$5<$D12),1,"") | G12: =IF(AND(G$5>=$C12,G$5<$D12),1,"") | H12: =IF(AND(H$5>=$C12,H$5<$D12),1,"") | I12: =IF(AND(I$5>=$C12,I$5<$D12),1,"") -> 1 | J12: =IF(AND(J$5>=$C12,J$5<$D12),1,"") -> 1 | K12: =IF(AND(K$5>=$C12,K$5<$D12),1,"") -> 1 | L12: =IF(AND(L$5>=$C12,L$5<$D12),1,"") -> 1 | M12: =IF(AND(M$5>=$C12,M$5<$D12),1,"") -> 1 | ... AL12: =IF(AND(AL$5>=$C12,AL$5<$D12),1,"")
B14: Likely bottlenecks
B15: Septic and grease redesign can add months and dominate cost.
B16: Hood recertification without documents.
B17: King County permit queue before the 2024 code switch on May 3, 2027.
B18: LCB timing stretches if the floor plan, funding or premises documents are incomplete.

Sheet Costs
A1: Cost estimates (low and high)
A2: Blank cells are unknown, not zero. Totals exclude them and the count below each total says how many are missing. Set Include to 0 to drop a line.
A5: Item | B5: Section | C5: Include (1/0) | D5: Low ($) | E5: High ($) | F5: Basis | G5: Note
A6: Records copies | B6: Rooms | C6: 1 | F6: Unknown | G6: Get from KC Permitting Records Center.
A7: Zoning and Historical Certification Letter | B7: Rooms | C7: 1 | F7: Unknown | G7: Per 2026 KC fee schedule; confirm with DLS.
A8: WA business license application | B8: Rooms | C8: 1 | D8: 50 | E8: 50 | F8: WAC 458-02-200 | G8: Non-refundable.
A9: Liability insurance or platform coverage | B9: Rooms | C9: 1 | F9: Unknown | G9: Get a quote. RCW 64.37 requires $1M or equivalent.
A10: Smoke and CO alarms, extinguishers | B10: Rooms | C10: 1 | D10: 100 | E10: 600 | F10: My planning estimate | G10: Verify against what the rooms already have.
A11: Public Health plan review and permit | B11: Kitchen and alcohol | C11: 1 | D11: 1764 | E11: 2500 | F11: PHSKC 2026 | G11: $1,008 plan review plus $756 Risk 2 permit as the low end.
A12: LCB annual license | B12: Kitchen and alcohol | C12: 1 | D12: 600 | E12: 2700 | F12: LCB 2026 | G12: Beer/wine $600; spirits, beer and wine up to $2,700.
A13: Hood fan, makeup air, duct | B13: Kitchen and alcohol | C13: 1 | D13: 8000 | E13: 60000 | F13: Estimate | G13: Widest range because there are no documents.
A14: UL 300 suppression | B14: Kitchen and alcohol | C14: 1 | D14: 3000 | E14: 8000 | F14: Estimate
A15: Grease interceptor (exterior) | B15: Kitchen and alcohol | C15: 1 | D15: 8000 | E15: 30000 | F15: Estimate
A16: Septic upgrade, if required | B16: Kitchen and alcohol | C16: 1 | D16: 0 | E16: 150000 | F16: Estimate | G16: Could be zero or the biggest line.
A17: King County permits: mechanical, fire, building | B17: Kitchen and alcohol | C17: 1 | D17: 2000 | E17: 15000 | F17: Estimate | G17: Check the 2026 fee schedule.
A18: Design: architect, engineer, OSS designer | B18: Kitchen and alcohol | C18: 1 | D18: 5000 | E18: 40000 | F18: Estimate
A20: Totals
A21: Section | D21: Low ($) | E21: High ($) | F21: Items with no number yet
A22: Rooms | D22: =SUMPRODUCT((B6:B18=A22)*(C6:C18)*(D6:D18)) -> 150 | E22: =SUMPRODUCT((B6:B18=A22)*(C6:C18)*(E6:E18)) -> 650 | F22: =SUMPRODUCT((B6:B18=A22)*(C6:C18=1)*(D6:D18="")) -> 3
A23: Kitchen and alcohol | D23: =SUMPRODUCT((B6:B18=A23)*(C6:C18)*(D6:D18)) -> 28364 | E23: =SUMPRODUCT((B6:B18=A23)*(C6:C18)*(E6:E18)) -> 308200 | F23: =SUMPRODUCT((B6:B18=A23)*(C6:C18=1)*(D6:D18="")) -> 0
A24: Everything | D24: =D22+D23 -> 28514 | E24: =E22+E23 -> 308850 | F24: =F22+F23 -> 3

Sheet Open Questions
A1: Open questions and records requests
A2: Each one narrows a risk in the other tabs. Status is yours to edit.
A4: # | B4: Question or record | C4: Where to ask | D4: Why it matters | E4: Status
A5: 1 | B5: King County permit history: original 1993 permit, Certificate of Occupancy, occupancy class, expired permits, code enforcement cases | C5: KC Permitting Records Center (online request) | D5: Shows whether nightly lodging for the rooms is already a permitted use. Decides the rooms-only timeline. | E5: Open
A6: 2 | B6: Public Health food permit and inspection history, and the last closure date | C6: PHSKC | D6: The closure date sets the 365-day status that triggers a full plan review. | E6: Open
A7: 3 | B7: OSS as-built and design flow | C7: PHSKC online OSS records search | D7: Tells you what the septic can handle before you design a restaurant around it. | E7: Open
A8: 4 | B8: LCB license history at the address (Lucy's Table about 2017 to 2018; a 2022 Burton Inn, Spa and Grill listing) | C8: LCB public records | D8: Prior licensee issues or conditions on the premises. | E8: Open
A9: 5 | B9: Landlord (J.T. Sheffield LLC): lease use clause, consent to the liquor license, roof fan removal history, who pays for septic and hood work | C9: Landlord and your attorney | D9: Cost allocation and whether the lease permits lodging, a bar and a kitchen. | E9: Open
A10: 6 | B10: Exact zoning, P-suffix text, whether hotel/motel or B&B is allowed, and any resident-operator condition | C10: KC DLS zoning letter | D10: Could change the whole lodging plan. | E10: Open
A11: 7 | B11: Parcel number: the one LoopNet page found lists 24012 Vashon Hwy SW, not 24007 | C11: KC parcel viewer | D11: Every lookup depends on the right parcel. | E11: Open
A12: 8 | B12: Water purveyor and backflow requirements | C12: Burton Water Co-op (verify) | D12: Commercial kitchens often need premises isolation. | E12: Open
A13: 9 | B13: Does King County require Fire Marshal operational permits for the restaurant? | C13: KC Fire Marshal | D13: Adds an annual cost and inspection. | E13: Open
A14: 10 | B14: Guest cap: 10 or 16 | C14: You | D14: Decides R-3 versus R-1 and the fire and egress scrutiny. | E14: Open
A15: 11 | B15: Target hours and seat count (assumed about 40) | C15: You | D15: Fifty or more occupants makes the dining room A-2. | E15: Open
A16: 12 | B16: Alcohol path and structure: Burton Inn LLC as licensee, or an operator subleasing | C16: You and your attorney | D16: Drives the entire LCB tab. | E16: Open

Sheet Sources
A1: Sources
A2: Official means a government or agency site. Secondary means verify before relying on it. Retrieved during research on Oct 13, 2026.
A4: # | B4: Publisher | C4: Reliability | D4: URL
A5: 1 | B5: LoopNet | C5: Secondary, verify | D5: https://www.loopnet.com/property/24012-vashon-hwy-sw-vashon-wa-98070/53033-1922039014/
A6: 2 | B6: King County | C6: Official | D6: https://cdn.kingcounty.gov/-/media/king-county/depts/local-services/director/subarea-plans/vashon-maury-island/vashon-subarea-plan-20200724.pdf?rev=bf6f142d42f440a8aab166d3e3caa3f3&hash=6F9B6AD55BEDC8CF66088F721C6FD48C
A7: 3 | B7: King County | C7: Official | D7: https://aqua.kingcounty.gov/council/clerk/OldOrdsMotions/Ordinance%2007870.pdf
A8: 4 | B8: King County | C8: Official | D8: https://cdn.kingcounty.gov/-/media/king-county/independent/governance-and-leadership/government-oversight/hearing-examiner/documents/decisions-recommendations/appeals/code-enforcement/2023/enfr210581_hu.pdf?rev=9340a4d4514745b7b2b7aa68afb29081&hash=F5E52C7715FDF24D86555F0B124CCE33
A9: 5 | B9: Vashon-Maury Island Beachcomber | C9: Local news | D9: https://www.vashonbeachcomber.com/news/burton-landmark-purchased-by-island-business/
A10: 6 | B10: NeighborWho | C10: Secondary, verify | D10: https://www.neighborwho.com/Vashon-Hwy-Vashon-WA-addresses/
A11: 7 | B11: Wikipedia | C11: Secondary, verify | D11: https://en.wikipedia.org/wiki/List_of_landmarks_in_King_County,_Washington
A12: 8 | B12: Vashon Sewer District | C12: Official | D12: https://www.vashonsewerdistrict.org/
A13: 9 | B13: King County | C13: Official | D13: https://cdn.kingcounty.gov/-/media/king-county/depts/dph/documents/about-public-health/board-of-health/boh-code-title-13.pdf
A14: 10 | B14: King County | C14: Official | D14: https://cdn.kingcounty.gov/-/media/king-county/depts/dph/documents/health-safety/environmental-health/training/septic-system-maintenance-food-establishments.pdf?hash=C23129672BA7905C3CBAE0ED885051C1&rev=ef12098f6bbe4e50a535ff7a46e3455e
A15: 11 | B15: WA State Building Code Council | C15: Official | D15: https://sbcc.wa.gov/sites/default/files/2024-02/2021%20IBC%20Insert%20Pages%202nd%20printing.pdf
A16: 12 | B16: WA State Building Code Council | C16: Official | D16: https://sbcc.wa.gov/
... A50: 46 | B50: Facebook (Burton Inn page) | C50: Secondary, verify | D50: https://www.facebook.com/BurtonInnVashon/
B52: Note: the one LoopNet page found is for 24012 Vashon Hwy SW. The zoning and size data attributed to 24007 in the research need a parcel check.
